pyquiver.libs/libfmt-8375f6bf.so.6.2.1
pyquiver.libs/libspdlog-a0a9d586.so.1.5.0
pyquiver/_quiver.cpython-39-x86_64-linux-gnu.so
pyquiver/collections.py
pyquiver/__init__.py
pyquiver-0.0.5.dist-info/entry_points.txt
pyquiver-0.0.5.dist-info/RECORD
pyquiver-0.0.5.dist-info/METADATA
pyquiver-0.0.5.dist-info/WHEEL
pyquiver-0.0.5.dist-info/licenses/LICENSE.txt
