Metadata-Version: 2.1
Name: pyquiver
Version: 0.0.5
License:                                  Apache License
Classifier: Development Status :: 2 - Pre-Alpha
Classifier: Intended Audience :: Developers
Classifier: Intended Audience :: Science/Research
Classifier: License :: OSI Approved :: Apache Software License
Classifier: Operating System :: POSIX :: Linux
Classifier: Programming Language :: C++
Classifier: Programming Language :: Python :: 3
Project-URL: Homepage, https://github.com/westonpace/quiver
Requires-Dist: pyarrow>=1.0.0
Requires-Dist: bumpver; extra == "dev"
Requires-Dist: pytest; extra == "dev"
Provides-Extra: dev
License-File: LICENSE.txt
